c_helpers/__init__.py
c_helpers/__main__.py
c_helpers/_version.py
c_helpers-1.0.0.dist-info/LICENSE
c_helpers-1.0.0.dist-info/METADATA
c_helpers-1.0.0.dist-info/WHEEL
c_helpers-1.0.0.dist-info/entry_points.txt
c_helpers-1.0.0.dist-info/top_level.txt
c_helpers-1.0.0.dist-info/RECORD
