Metadata-Version: 2.1
Name: c-helpers
Version: 1.0.0
Summary: Helpers for c-structs sizes and offsets
Author-email: doronz88 <doron88@gmail.com>
Maintainer-email: doronz88 <doron88@gmail.com>
License: MIT
Project-URL: Homepage, https://github.com/doronz88/c-helpers
Project-URL: Bug Reports, https://github.com/doronz88/c-helpers/issues
Keywords: c,struct
Classifier: Development Status :: 5 - Production/Stable
Classifier: License :: OSI Approved :: MIT License
Classifier: Programming Language :: Python :: 3
Classifier: Programming Language :: Python :: 3.8
Classifier: Programming Language :: Python :: 3.9
Classifier: Programming Language :: Python :: 3.10
Classifier: Programming Language :: Python :: 3.11
Classifier: Programming Language :: Python :: 3.12
Classifier: Programming Language :: Python :: 3 :: Only
Requires-Python: >=3.8
License-File: LICENSE
Requires-Dist: click
Requires-Dist: plumbum
Provides-Extra: test
Requires-Dist: pytest ; extra == 'test'
